{
  "terms": [
    {
      "source": "machine learning",
      "target": "apprentissage automatique",
      "language": "fr",
      "domain": "technology",
      "notes": "Preferred term over 'apprentissage machine'"
    },
    {
      "source": "artificial intelligence",
      "target": "intelligence artificielle",
      "language": "fr",
      "domain": "technology",
      "notes": ""
    },
    {
      "source": "neural network",
      "target": "réseau de neurones",
      "language": "fr",
      "domain": "technology",
      "notes": ""
    },
    {
      "source": "database",
      "target": "base de données",
      "language": "fr",
      "domain": "technology",
      "notes": ""
    },
    {
      "source": "software",
      "target": "logiciel",
      "language": "fr",
      "domain": "technology",
      "notes": "Do not use 'software' as a loanword"
    }
  ],
  "style_rules": [
    "Use formal register",
    "Avoid contractions",
    "Keep sentences under 30 words where possible",
    "Use Oxford comma"
  ]
}
